rrLovesbb/__init__.py
rrLovesbb-0.0.1.dist-info/LICENSE
rrLovesbb-0.0.1.dist-info/METADATA
rrLovesbb-0.0.1.dist-info/WHEEL
rrLovesbb-0.0.1.dist-info/top_level.txt
rrLovesbb-0.0.1.dist-info/RECORD
