Metadata-Version: 2.1
Name: rrLovesbb
Version: 0.0.1
Summary: rr
Home-page: https://hack.md
Author: tzrj
Author-email: tzrj@zeroday.com
License: UNKNOWN
Platform: UNKNOWN
Classifier: Programming Language :: Python :: 3
Classifier: License :: OSI Approved :: MIT License
Classifier: Operating System :: OS Independent
Requires-Python: >=3.0
License-File: LICENSE
